mac_notifier/__init__.py
mac_notifier/main.py
mac_notifier-0.0.3.dist-info/METADATA
mac_notifier-0.0.3.dist-info/WHEEL
mac_notifier-0.0.3.dist-info/entry_points.txt
mac_notifier-0.0.3.dist-info/top_level.txt
mac_notifier-0.0.3.dist-info/RECORD
