Metadata-Version: 2.1
Name: mac-notifier
Version: 0.0.3
Summary: Display notifications, alerts and dialogs on mac from command line
Home-page: https://github.com/xirenhua/mac_notifier
Author: xirenhua
Author-email: xirenhua@outlook.com
License: UNKNOWN
Platform: UNKNOWN
Requires-Dist: click
